speech_prep/__init__.py
speech_prep/core.py
speech_prep/detection.py
speech_prep/exceptions.py
speech_prep/formats.py
speech_prep/processing.py
speech_prep/utils.py
speech_prep-0.1.4.dist-info/METADATA
speech_prep-0.1.4.dist-info/WHEEL
speech_prep-0.1.4.dist-info/licenses/LICENSE
speech_prep-0.1.4.dist-info/RECORD
