Metadata-Version: 2.4
Name: speech-prep
Version: 0.1.4
Summary: Audio preprocessing toolkit for speech-to-text applications using ffmpeg
Project-URL: Homepage, https://github.com/dimdasci/speech-prep
Project-URL: Repository, https://github.com/dimdasci/speech-prep
Project-URL: Issues, https://github.com/dimdasci/speech-prep/issues
Author-email: Dim Kharitonov <dimds@fastmail.com>
License: MIT
License-File: LICENSE
Keywords: audio,ffmpeg,preprocessing,silence-detection,speech-to-text
Classifier: Development Status :: 3 - Alpha
Classifier: Intended Audience :: Developers
Classifier: License :: OSI Approved :: MIT License
Classifier: Programming Language :: Python :: 3
Classifier: Programming Language :: Python :: 3.9
Classifier: Programming Language :: Python :: 3.10
Classifier: Programming Language :: Python :: 3.11
Classifier: Programming Language :: Python :: 3.12
Classifier: Topic :: Multimedia :: Sound/Audio
Classifier: Topic :: Software Development :: Libraries :: Python Modules
Requires-Python: >=3.9
Provides-Extra: dev
